rangefilter/__init__.py
rangefilter/admin.py
rangefilter/apps.py
rangefilter/filter.py
rangefilter/filters.py
rangefilter/forms.py
rangefilter/models.py
rangefilter/settings.py
rangefilter/locale/cs_CZ/LC_MESSAGES/django.mo
rangefilter/locale/cs_CZ/LC_MESSAGES/django.po
rangefilter/locale/da/LC_MESSAGES/django.mo
rangefilter/locale/da/LC_MESSAGES/django.po
rangefilter/locale/de/LC_MESSAGES/django.mo
rangefilter/locale/de/LC_MESSAGES/django.po
rangefilter/locale/el/LC_MESSAGES/django.mo
rangefilter/locale/el/LC_MESSAGES/django.po
rangefilter/locale/en_US/LC_MESSAGES/django.mo
rangefilter/locale/en_US/LC_MESSAGES/django.po
rangefilter/locale/es/LC_MESSAGES/django.mo
rangefilter/locale/es/LC_MESSAGES/django.po
rangefilter/locale/es_AR/LC_MESSAGES/django.mo
rangefilter/locale/es_AR/LC_MESSAGES/django.po
rangefilter/locale/fa/LC_MESSAGES/django.mo
rangefilter/locale/fa/LC_MESSAGES/django.po
rangefilter/locale/fr/LC_MESSAGES/django.mo
rangefilter/locale/fr/LC_MESSAGES/django.po
rangefilter/locale/it/LC_MESSAGES/django.mo
rangefilter/locale/it/LC_MESSAGES/django.po
rangefilter/locale/ja/LC_MESSAGES/django.mo
rangefilter/locale/ja/LC_MESSAGES/django.po
rangefilter/locale/pl/LC_MESSAGES/django.mo
rangefilter/locale/pl/LC_MESSAGES/django.po
rangefilter/locale/pt_BR/LC_MESSAGES/django.mo
rangefilter/locale/pt_BR/LC_MESSAGES/django.po
rangefilter/locale/pt_PT/LC_MESSAGES/django.mo
rangefilter/locale/pt_PT/LC_MESSAGES/django.po
rangefilter/locale/ru/LC_MESSAGES/django.mo
rangefilter/locale/ru/LC_MESSAGES/django.po
rangefilter/locale/uk/LC_MESSAGES/django.mo
rangefilter/locale/uk/LC_MESSAGES/django.po
rangefilter/locale/zh_CN/LC_MESSAGES/django.mo
rangefilter/locale/zh_CN/LC_MESSAGES/django.po
rangefilter/locale/zh_Hans/LC_MESSAGES/django.mo
rangefilter/locale/zh_Hans/LC_MESSAGES/django.po
rangefilter/static/css/admin-numeric-filter.css
rangefilter/static/css/nouislider.min.css
rangefilter/static/js/admin-numeric-filter.js
rangefilter/static/js/nouislider.min.css
django_rangefilter-0.9.1.dist-info/LICENSE
django_rangefilter-0.9.1.dist-info/METADATA
django_rangefilter-0.9.1.dist-info/WHEEL
django_rangefilter-0.9.1.dist-info/top_level.txt
django_rangefilter-0.9.1.dist-info/RECORD
